mmLib/create_monomers.sh
mmLib/PDB.py
mmLib/Structure.py
mmLib/UnitCell.py
mmLib/mmCIFBuilder.py
mmLib/CIFBuilder.py
mmLib/SpaceGroups.py
mmLib/Sequence.py
mmLib/Gaussian.py
mmLib/ConsoleOutput.py
mmLib/PDBBuilder.py
mmLib/Constants.py
mmLib/Library.py
mmLib/__init__.py
mmLib/StructureBuilder.py
mmLib/Colors.py
mmLib/TLS.py
mmLib/Superposition.py
mmLib/NumericCompat.py
mmLib/GeometryDict.py
mmLib/FileIO.py
mmLib/Viewer.py
mmLib/pdbmodule.cpython-313-x86_64-linux-gnu.so
mmLib/OpenGLDriver.py
mmLib/CIF.py
mmLib/mmCIFDB.py
mmLib/build_library.py
mmLib/AtomMath.py
mmLib/mmCIF.py
mmLib/R3DDriver.py
mmLib/Data/monomers.cif
mmLib/Data/elements.cif
pymmlib3-2.1.0.dist-info/LICENSE.txt
pymmlib3-2.1.0.dist-info/entry_points.txt
pymmlib3-2.1.0.dist-info/RECORD
pymmlib3-2.1.0.dist-info/METADATA
pymmlib3-2.1.0.dist-info/WHEEL
pymmlib3-2.1.0.dist-info/top_level.txt
pymmlib3-2.1.0.dist-info/AUTHORS.txt
