Metadata-Version: 2.1
Name: pymmlib3
Version: 2.1.0
Summary: mmLib-2.0: Python Macromolecular Library (mmLib), based on the Python 2.4 library: https://pymmlib.sourceforge.net/
Home-page: https://github.com/prubach/pymmlib3
Author: Pawel Rubach, originally: Jay Painter
Author-email: pawel.rubach@gmail.com
Classifier: Programming Language :: Python :: 3
Classifier: Programming Language :: Python :: 3.8
Classifier: Programming Language :: Python :: 3.9
Classifier: Programming Language :: Python :: 3.10
Classifier: Programming Language :: Python :: 3.11
Classifier: Programming Language :: Python :: 3.12
Classifier: Programming Language :: Python :: 3.13
Classifier: License :: OSI Approved :: Artistic License
Classifier: Operating System :: Unix
Classifier: Operating System :: POSIX :: Linux
Classifier: Operating System :: MacOS :: MacOS X
Classifier: Operating System :: Microsoft :: Windows
Requires-Python: >=3.8.0
License-File: LICENSE.txt
License-File: AUTHORS.txt
Requires-Dist: numpy
